MEDS_trajectory_evaluation/__init__.py
MEDS_trajectory_evaluation/aces_utils.py
MEDS_trajectory_evaluation/schema.py
MEDS_trajectory_evaluation/ACES_config_evaluation/__init__.py
MEDS_trajectory_evaluation/ACES_config_evaluation/__main__.py
MEDS_trajectory_evaluation/ACES_config_evaluation/label.py
MEDS_trajectory_evaluation/ACES_config_evaluation/task_config.py
MEDS_trajectory_evaluation/ACES_config_evaluation/utils.py
MEDS_trajectory_evaluation/ACES_config_evaluation/configs/__init__.py
MEDS_trajectory_evaluation/ACES_config_evaluation/configs/_label.yaml
MEDS_trajectory_evaluation/temporal_AUC_evaluation/__init__.py
MEDS_trajectory_evaluation/temporal_AUC_evaluation/get_ttes.py
MEDS_trajectory_evaluation/temporal_AUC_evaluation/temporal_AUCS.py
MEDS_trajectory_evaluation/temporal_AUC_evaluation/trajectory_AUC.py
meds_trajectory_evaluation-0.0.5.dist-info/licenses/LICENSE
meds_trajectory_evaluation-0.0.5.dist-info/METADATA
meds_trajectory_evaluation-0.0.5.dist-info/WHEEL
meds_trajectory_evaluation-0.0.5.dist-info/entry_points.txt
meds_trajectory_evaluation-0.0.5.dist-info/top_level.txt
meds_trajectory_evaluation-0.0.5.dist-info/RECORD
