Metadata-Version: 2.4
Name: MEDS_trajectory_evaluation
Version: 0.0.5
Summary: A framework for extracting labels from generated trajectories for arbitrary ACES configs.
Author-email: Matthew McDermott <mattmcdermott8@gmail.com>
Project-URL: Homepage, https://github.com/mmcdermott/MEDS_trajectory_evaluation
Project-URL: Issues, https://github.com/mmcdermott/MEDS_trajectory_evaluation/issues
Classifier: Programming Language :: Python :: 3
Classifier: License :: OSI Approved :: MIT License
Classifier: Operating System :: OS Independent
Requires-Python: >=3.11
License-File: LICENSE
Requires-Dist: meds~=0.4.0
Requires-Dist: es-aces>=0.7.0
Requires-Dist: hydra-core
Requires-Dist: MEDS-transforms~=0.5.0
Requires-Dist: flexible_schema
Requires-Dist: pytimeparse
Provides-Extra: dev
Requires-Dist: pre-commit<4; extra == "dev"
Requires-Dist: ruff; extra == "dev"
Provides-Extra: tests
Requires-Dist: pytest; extra == "tests"
Requires-Dist: pytest-cov; extra == "tests"
Requires-Dist: pretty-print-directory; extra == "tests"
Requires-Dist: hypothesis; extra == "tests"
Requires-Dist: scikit-learn; extra == "tests"
Dynamic: license-file
